allocmd/__init__.py
allocmd/cli.py
allocmd/templates/Dockerfile.j2
allocmd/templates/config.yaml.j2
allocmd/templates/dev-docker-compose.yaml.j2
allocmd/templates/env.j2
allocmd/templates/gitignore.j2
allocmd/templates/init.sh.j2
allocmd/templates/main.py.j2
allocmd/templates/prod-docker-compose.yaml.j2
allocmd/templates/requirements.txt.j2
allocmd/templates/start-validator.sh.j2
allocmd/templates/update-node-ip.sh.j2
allocmd/templates/validator-docker-compose.yaml.j2
allocmd/templates/validator.values.yaml.j2
allocmd/templates/worker.values.yaml.j2
allocmd/utilities/__init__.py
allocmd/utilities/constants.py
allocmd/utilities/typings.py
allocmd/utilities/utils.py
allocmd-2.0.10.dist-info/LICENSE
allocmd-2.0.10.dist-info/METADATA
allocmd-2.0.10.dist-info/WHEEL
allocmd-2.0.10.dist-info/entry_points.txt
allocmd-2.0.10.dist-info/top_level.txt
allocmd-2.0.10.dist-info/RECORD
